naixi_key_encryptor-0.1.1.dist-info/METADATA
naixi_key_encryptor-0.1.1.dist-info/WHEEL
naixi_key_encryptor/__init__.py
naixi_key_encryptor/__pycache__/__init__.cpython-313.pyc
naixi_key_encryptor_native/__init__.py
naixi_key_encryptor_native/naixi_key_encryptor_native.cpython-313-darwin.so
naixi_key_encryptor-0.1.1.dist-info/RECORD
