Metadata-Version: 2.4
Name: naixi-key-encryptor
Version: 0.1.1
Classifier: Programming Language :: Python
Classifier: Programming Language :: Python :: 3
Classifier: Programming Language :: Rust
Classifier: Topic :: Security :: Cryptography
Summary: Python bindings for the naixi key encryptor
Author: naixi
Requires-Python: >=3.8
Project-URL: Homepage, https://github.com/naixiWeb3/naixi-key-encryptor
